text2file/__init__.py
text2file/__main__.py
text2file/cli.py
text2file/generators/__init__.py
text2file/generators/archives.py
text2file/generators/base.py
text2file/generators/config.py
text2file/generators/excel.py
text2file/generators/image/__init__.py
text2file/generators/image/jpg_generator.py
text2file/generators/image/svg_generator.py
text2file/generators/image_set.py
text2file/generators/images.py
text2file/generators/office.py
text2file/generators/pdf/__init__.py
text2file/generators/registration.py
text2file/generators/text/__init__.py
text2file/generators/text/markdown_generator.py
text2file/generators/text/python_generator.py
text2file/generators/text/sh_generator.py
text2file/generators/validators.py
text2file/generators/video.py
text2file/generators/xlsx_generator.py
text2file/utils/file_utils.py
text2file/utils/image_utils.py
text2file/utils/text_utils.py
text2file/validators/__init__.py
text2file/validators/archive_validator.py
text2file/validators/base.py
text2file/validators/image_validator.py
text2file/validators/office_validator.py
text2file/validators/pdf_validator.py
text2file/validators/text/markdown_validator.py
text2file/validators/text/shell_validator.py
text2file/validators/text_validator.py
text2file/validators/video_validator.py
text2file-0.1.17.dist-info/LICENSE
text2file-0.1.17.dist-info/METADATA
text2file-0.1.17.dist-info/WHEEL
text2file-0.1.17.dist-info/RECORD
