Metadata-Version: 2.3
Name: text2file
Version: 0.1.17
Summary: A utility to generate test files in various formats from text content
License: Apache 2.0
Author: Tom Sapletta
Author-email: info@softreck.dev
Requires-Python: >=3.8,<4.0
Classifier: License :: Other/Proprietary License
Classifier: Programming Language :: Python :: 3
Classifier: Programming Language :: Python :: 3.8
Classifier: Programming Language :: Python :: 3.9
Classifier: Programming Language :: Python :: 3.10
Classifier: Programming Language :: Python :: 3.11
Classifier: Programming Language :: Python :: 3.12
Classifier: Programming Language :: Python :: 3.13
Provides-Extra: video
Requires-Dist: Pillow (>=10.0.0,<11.0.0) ; extra == "video"
Requires-Dist: PyYAML (>=6.0.1,<7.0.0)
Requires-Dist: click (>=8.1.3,<9.0.0)
Requires-Dist: moviepy (>=1.0.3,<2.0.0) ; extra == "video"
Requires-Dist: numpy (>=1.24.0,<2.0.0) ; extra == "video"
Requires-Dist: opencv-python (>=4.8.0,<5.0.0) ; extra == "video"
Requires-Dist: rich (>=14.0.0,<15.0.0)
Requires-Dist: tomli (>=2.0.1,<3.0.0) ; python_version < "3.11"
